async_appwrite/__init__.py
async_appwrite/async_client.py
async_appwrite/async_service.py
async_appwrite/services/__init__.py
async_appwrite/services/async_account.py
async_appwrite/services/async_avatars.py
async_appwrite/services/async_databases.py
async_appwrite/services/async_functions.py
async_appwrite/services/async_graphql.py
async_appwrite/services/async_health.py
async_appwrite/services/async_locale.py
async_appwrite/services/async_messaging.py
async_appwrite/services/async_storage.py
async_appwrite/services/async_teams.py
async_appwrite/services/async_users.py
async_appwrite-1.0.0.dist-info/LICENSE
async_appwrite-1.0.0.dist-info/METADATA
async_appwrite-1.0.0.dist-info/WHEEL
async_appwrite-1.0.0.dist-info/top_level.txt
async_appwrite-1.0.0.dist-info/RECORD
