Metadata-Version: 2.1
Name: async-appwrite
Version: 1.0.0
Summary: Appwrite is an open-source self-hosted backend server that abstract and simplify complex and repetitive development tasks behind a very simple REST API
Home-page: UNKNOWN
Author: Umar Saadu
Author-email: saaduumar42@gmail.com
Maintainer: Umar Saadu
Maintainer-email: saaduumar42@gmail.com
License: BSD-3-Clause
Platform: UNKNOWN
Classifier: Development Status :: 5 - Production/Stable
Classifier: Intended Audience :: Developers
Classifier: Environment :: Web Environment
Classifier: Topic :: Software Development
Classifier: License :: OSI Approved :: BSD License
Classifier: Programming Language :: Python :: 3
Classifier: Programming Language :: Python :: 3.5
Classifier: Programming Language :: Python :: 3.6
Classifier: Programming Language :: Python :: 3.7
Classifier: Programming Language :: Python :: 3.8
Requires-Dist: requests
Requires-Dist: appwrite
Requires-Dist: httpx
